stackunflow/__init__.py
stackunflow/locales/en.json
stackunflow/locales/id.json
stackunflow-0.3.0.dist-info/METADATA
stackunflow-0.3.0.dist-info/WHEEL
stackunflow-0.3.0.dist-info/top_level.txt
stackunflow-0.3.0.dist-info/RECORD
