Metadata-Version: 2.4
Name: stackunflow
Version: 0.3.0
Summary: The ultimate anti-productivity toolkit. When you're stuck, StackUnflow helps you get even more stuck.
Author-email: AntonCalderon <antoncalderon1105@gmail.com>
Keywords: procrastination,debug,funny,satire,burnout,i18n
Classifier: Development Status :: 3 - Alpha
Classifier: Intended Audience :: Developers
Classifier: License :: OSI Approved :: MIT License
Classifier: Programming Language :: Python :: 3
Requires-Python: >=3.7
